{
  "title": "Blog statistics after two years",
  "link": "https://nfraprado.net/post/blog-statistics-after-two-years.html",
  "pubDate": "2022-06-20T03:00:00.000Z",
  "snippet": "<p>Wow, it's been two years since I've started this blog! I'm really happy that\nI've still managed to keep up the one post per month. Hopefully I'll be able to\nkeep it up for the third one!</p>\n<p>For this post I thought it would be fun to look through some …</p>",
  "author": "Nicolas F. R. A. Prado",
  "feedSource": "https://nfraprado.net/feeds/all.atom.xml",
  "lastFetched": "2025-02-22T22:06:26.063Z"
}