{
  "title": "Moving the blog to Codeberg",
  "link": "https://nfraprado.net/post/moving-the-blog-to-codeberg.html",
  "pubDate": "2022-08-29T03:00:00.000Z",
  "snippet": "<p>As someone who cares about FOSS, I'm always happy to move to a FOSS alternative\nwhen one shows up, provided there aren't any big drawbacks.</p>\n<p>Back when I was in University and starting to learn the ways of Git, I only knew\nabout two Git hosting options: GitHub, the mainstream …</p>",
  "author": "Nicolas F. R. A. Prado",
  "feedSource": "https://nfraprado.net/feeds/all.atom.xml",
  "lastFetched": "2025-02-22T22:31:20.966Z"
}